Metadata-Version: 1.1
Name: gen-cisco
Version: 1.2.5
Summary: Generates Cisco scripts based on YAML files
Home-page: https://github.com/rememberYou/gen-cisco
Author: Terencio Agozzino
Author-email: terencio.agozzino@gmail.com
License: MIT
Project-URL: Source, https://github.com/rememberYou/gen-cisco
Project-URL: Tracker, https://github.com/rememberYou/gen-cisco/issues
Keywords: cisco ccna generate netacad packettracer python script scripts
Platform: UNKNOWN
Classifier: Development Status :: 3 - Alpha
Classifier: Intended Audience :: System Administrators
Classifier: License :: OSI Approved :: MIT License
Classifier: Natural Language :: English
Classifier: Programming Language :: Python
Classifier: Programming Language :: Python :: 3.0
Classifier: Programming Language :: Python :: 3.1
Classifier: Programming Language :: Python :: 3.2
Classifier: Programming Language :: Python :: 3.3
Classifier: Programming Language :: Python :: 3.4
Classifier: Programming Language :: Python :: 3.5
Classifier: Programming Language :: Python :: 3.6
Classifier: Programming Language :: Python :: 3.7
Classifier: Programming Language :: Python :: 3 :: Only
Classifier: Topic :: Utilities
